LICENSE
MANIFEST.in
README.rst
setup.cfg
setup.py
versioneer.py
artellapipe/__init__.py
artellapipe/libs/__init__.py
artellapipe/libs/picker/__init__.py
artellapipe/libs/picker/__logging__.ini
artellapipe/libs/picker/__version__.py
artellapipe/libs/picker/_version.py
artellapipe_libs_picker.egg-info/PKG-INFO
artellapipe_libs_picker.egg-info/SOURCES.txt
artellapipe_libs_picker.egg-info/dependency_links.txt
artellapipe_libs_picker.egg-info/not-zip-safe
artellapipe_libs_picker.egg-info/requires.txt
artellapipe_libs_picker.egg-info/top_level.txt
tests/__init__.py
tests/test_general.py