Metadata-Version: 2.1
Name: artellapipe-libs-picker
Version: 0.0.1
Summary: Library to create data driven based pickers for rigs
Home-page: https://github.com/ArtellaPipe/artellapipe-libs-picker
Author: Tomas Poveda
Author-email: tpovedatd@gmail.com
License: MIT
Platform: UNKNOWN
Provides-Extra: dev
Provides-Extra: test
